{
  "generatedAt": "2026-07-18T02:35:53.605Z",
  "league": "Runes of Aldur",
  "minIlvl": 70,
  "divineRate": 440,
  "categories": [
    {
      "key": "armour.chest/ar/ev",
      "label": "Body Armour — Armour + Evasion",
      "group": "Body Armour / ar/ev",
      "section": "Armour",
      "at": "2026-07-17T13:35:15.842Z",
      "minIlvl": 70,
      "total": 1538,
      "ladder": [
        {
          "minEx": 1,
          "count": 1538
        },
        {
          "minEx": 50,
          "count": 767
        },
        {
          "minEx": 200,
          "count": 598
        },
        {
          "minEx": 1000,
          "count": 218
        },
        {
          "minEx": 5000,
          "count": 71
        }
      ],
      "dearThresholdEx": 1000,
      "dearCount": 218,
      "nDear": 100,
      "nBase": 100,
      "snapshots": 1,
      "trendPct": null,
      "bases": [
        {
          "key": "Death Mail",
          "label": "Death Mail",
          "lift": 0.9166666666666667,
          "ciLow": 0.5516709540561978,
          "ciHigh": 1.5231502974727578,
          "inDear": 22,
          "inBase": 24,
          "shareDear": 0.22,
          "shareBase": 0.24,
          "significant": false
        },
        {
          "key": "Dastard Armour",
          "label": "Dastard Armour",
          "lift": 0.9166666666666667,
          "ciLow": 0.5516709540561978,
          "ciHigh": 1.5231502974727578,
          "inDear": 22,
          "inBase": 24,
          "shareDear": 0.22,
          "shareBase": 0.24,
          "significant": false
        },
        {
          "key": "Shrouded Mail",
          "label": "Shrouded Mail",
          "lift": 0.8333333333333334,
          "ciLow": 0.49310856411383786,
          "ciHigh": 1.4082992975237127,
          "inDear": 20,
          "inBase": 24,
          "shareDear": 0.2,
          "shareBase": 0.24,
          "significant": false
        }
      ],
      "prefixes": [
        {
          "key": "exp|#% increased Armour and Evasion",
          "label": "#% increased Armour and Evasion",
          "lift": 1.3888888888888888,
          "ciLow": 1.0018390893596416,
          "ciHigh": 1.925471232023901,
          "inDear": 50,
          "inBase": 36,
          "shareDear": 0.5,
          "shareBase": 0.36,
          "significant": true,
          "desecrated": false,
          "tierRange": "P1-P8",
          "tierDear": "P2",
          "tierMarket": "P3"
        },
        {
          "key": "exp|# to Armour / # to Evasion Rating / #% increased Armour and Evasion",
          "label": "# to Armour / # to Evasion Rating / #% increased Armour and Evasion",
          "lift": 1.3333333333333333,
          "ciLow": 0.8805220392260807,
          "ciHigh": 2.019004293566943,
          "inDear": 36,
          "inBase": 27,
          "shareDear": 0.36,
          "shareBase": 0.27,
          "significant": false,
          "desecrated": false,
          "tierRange": "P1-P6",
          "tierDear": "P2",
          "tierMarket": "P2"
        },
        {
          "key": "exp|# to Armour / # to Evasion Rating",
          "label": "# to Armour / # to Evasion Rating",
          "lift": 1.0952380952380953,
          "ciLow": 0.8006642597237928,
          "ciHigh": 1.4981891232094984,
          "inDear": 46,
          "inBase": 42,
          "shareDear": 0.46,
          "shareBase": 0.42,
          "significant": false,
          "desecrated": false,
          "tierRange": "P1-P7",
          "tierDear": "P2",
          "tierMarket": "P3"
        },
        {
          "key": "exp|# to maximum Life / #% increased Armour and Evasion",
          "label": "#% increased Armour and Evasion / # to maximum Life",
          "lift": 1,
          "ciLow": 0.6339563831287481,
          "ciHigh": 1.5773955852683847,
          "inDear": 27,
          "inBase": 27,
          "shareDear": 0.27,
          "shareBase": 0.27,
          "significant": false,
          "desecrated": false,
          "tierRange": "P1-P6",
          "tierDear": "P1",
          "tierMarket": "P2"
        },
        {
          "key": "exp|# to maximum Life",
          "label": "# to maximum Life",
          "lift": 0.8444444444444444,
          "ciLow": 0.606419675818141,
          "ciHigh": 1.1758959153016229,
          "inDear": 38,
          "inBase": 45,
          "shareDear": 0.38,
          "shareBase": 0.45,
          "significant": false,
          "desecrated": false,
          "tierRange": "P1-P12",
          "tierDear": "P3",
          "tierMarket": "P4"
        },
        {
          "key": "exp|# to # Physical Thorns damage",
          "label": "# to # Physical Thorns damage",
          "lift": 0.6470588235294117,
          "ciLow": 0.3194102344651639,
          "ciHigh": 1.310806843144313,
          "inDear": 11,
          "inBase": 17,
          "shareDear": 0.11,
          "shareBase": 0.17,
          "significant": false,
          "desecrated": false,
          "tierRange": "P1-P6",
          "tierDear": "P2",
          "tierMarket": "P2"
        }
      ],
      "suffixes": [
        {
          "key": "exp|Gain Deflection Rating equal to #% of Evasion Rating",
          "label": "Gain Deflection Rating equal to #% of Evasion Rating",
          "lift": 3,
          "ciLow": 1.2426142600221073,
          "ciHigh": 7.242794718805079,
          "inDear": 18,
          "inBase": 6,
          "shareDear": 0.18,
          "shareBase": 0.06,
          "significant": true,
          "desecrated": false,
          "tierRange": "S1-S3",
          "tierDear": "S2",
          "tierMarket": "S2"
        },
        {
          "key": "exp|#% to Lightning Resistance",
          "label": "#% to Lightning Resistance",
          "lift": 1.2580645161290323,
          "ciLow": 0.8589949327761829,
          "ciHigh": 1.8425327861105862,
          "inDear": 39,
          "inBase": 31,
          "shareDear": 0.39,
          "shareBase": 0.31,
          "significant": false,
          "desecrated": false,
          "tierRange": "S1-S8",
          "tierDear": "S2",
          "tierMarket": "S3"
        },
        {
          "key": "exp|#% to Cold Resistance",
          "label": "#% to Cold Resistance",
          "lift": 1.0263157894736843,
          "ciLow": 0.7229586071633449,
          "ciHigh": 1.456963219313335,
          "inDear": 39,
          "inBase": 38,
          "shareDear": 0.39,
          "shareBase": 0.38,
          "significant": false,
          "desecrated": false,
          "tierRange": "S1-S5",
          "tierDear": "S2",
          "tierMarket": "S3"
        },
        {
          "key": "exp|# to Stun Threshold",
          "label": "# to Stun Threshold",
          "lift": 1.0526315789473684,
          "ciLow": 0.5992223167523283,
          "ciHigh": 1.8491187828293187,
          "inDear": 20,
          "inBase": 19,
          "shareDear": 0.2,
          "shareBase": 0.19,
          "significant": false,
          "desecrated": false,
          "tierRange": "S1-S8",
          "tierDear": "S3",
          "tierMarket": "S2"
        },
        {
          "key": "exp|# to Strength",
          "label": "# to Strength",
          "lift": 1.3,
          "ciLow": 0.5980621033558006,
          "ciHigh": 2.8257934928784167,
          "inDear": 13,
          "inBase": 10,
          "shareDear": 0.13,
          "shareBase": 0.1,
          "significant": false,
          "desecrated": false,
          "tierRange": "S1-S5",
          "tierDear": "S2",
          "tierMarket": "S2"
        },
        {
          "key": "exp|#% to Fire Resistance",
          "label": "#% to Fire Resistance",
          "lift": 0.9062499999999999,
          "ciLow": 0.5959548542395166,
          "ciHigh": 1.3781061713945206,
          "inDear": 29,
          "inBase": 32,
          "shareDear": 0.29,
          "shareBase": 0.32,
          "significant": false,
          "desecrated": false,
          "tierRange": "S1-S8",
          "tierDear": "S2",
          "tierMarket": "S2"
        }
      ]
    },
    {
      "key": "armour.gloves/ar",
      "label": "Gloves — Armour",
      "group": "Gloves / ar",
      "section": "Armour",
      "at": "2026-07-17T22:37:42.279Z",
      "minIlvl": 70,
      "total": 1402,
      "ladder": [
        {
          "minEx": 1,
          "count": 1402
        },
        {
          "minEx": 50,
          "count": 876
        },
        {
          "minEx": 200,
          "count": 662
        },
        {
          "minEx": 1000,
          "count": 293
        },
        {
          "minEx": 5000,
          "count": 115
        }
      ],
      "dearThresholdEx": 1000,
      "dearCount": 293,
      "nDear": 100,
      "nBase": 100,
      "snapshots": 1,
      "trendPct": null,
      "bases": [
        {
          "key": "Massive Mitts",
          "label": "Massive Mitts",
          "lift": 0.9259259259259258,
          "ciLow": 0.5798089471062339,
          "ciHigh": 1.4786574518738833,
          "inDear": 25,
          "inBase": 27,
          "shareDear": 0.25,
          "shareBase": 0.27,
          "significant": false
        },
        {
          "key": "Vaal Mitts",
          "label": "Vaal Mitts",
          "lift": 0.8695652173913043,
          "ciLow": 0.5111681565680364,
          "ciHigh": 1.4792464232778235,
          "inDear": 20,
          "inBase": 23,
          "shareDear": 0.2,
          "shareBase": 0.23,
          "significant": false
        },
        {
          "key": "Ornate Mitts",
          "label": "Ornate Mitts",
          "lift": 1.2380952380952381,
          "ciLow": 0.7480643088670343,
          "ciHigh": 2.0491283976850823,
          "inDear": 26,
          "inBase": 21,
          "shareDear": 0.26,
          "shareBase": 0.21,
          "significant": false
        }
      ],
      "prefixes": [
        {
          "key": "exp|Adds # to # Lightning damage to Attacks",
          "label": "Adds # to # Lightning damage to Attacks",
          "lift": 1.7,
          "ciLow": 1.054311017346476,
          "ciHigh": 2.741126624355729,
          "inDear": 34,
          "inBase": 20,
          "shareDear": 0.34,
          "shareBase": 0.2,
          "significant": true,
          "desecrated": false,
          "tierRange": "P1-P5",
          "tierDear": "P3",
          "tierMarket": "P3"
        },
        {
          "key": "exp|#% increased Armour",
          "label": "#% increased Armour",
          "lift": 1.380952380952381,
          "ciLow": 0.8473315724488756,
          "ciHigh": 2.250629553371342,
          "inDear": 29,
          "inBase": 21,
          "shareDear": 0.29,
          "shareBase": 0.21,
          "significant": false,
          "desecrated": false,
          "tierRange": "P1-P5",
          "tierDear": "P2",
          "tierMarket": "P2"
        },
        {
          "key": "exp|Adds # to # Cold damage to Attacks",
          "label": "Adds # to # Cold damage to Attacks",
          "lift": 1.4999999999999998,
          "ciLow": 0.8094641502055334,
          "ciHigh": 2.77961661356923,
          "inDear": 21,
          "inBase": 14,
          "shareDear": 0.21,
          "shareBase": 0.14,
          "significant": false,
          "desecrated": false,
          "tierRange": "P1-P6",
          "tierDear": "P3",
          "tierMarket": "P4"
        },
        {
          "key": "exp|Adds # to # Physical Damage to Attacks",
          "label": "Adds # to # Physical Damage to Attacks",
          "lift": 1.1142857142857143,
          "ciLow": 0.7754436587640863,
          "ciHigh": 1.6011900271905728,
          "inDear": 39,
          "inBase": 35,
          "shareDear": 0.39,
          "shareBase": 0.35,
          "significant": false,
          "desecrated": false,
          "tierRange": "P1-P9",
          "tierDear": "P3",
          "tierMarket": "P4"
        },
        {
          "key": "exp|# to maximum Life",
          "label": "# to maximum Life",
          "lift": 0.8571428571428572,
          "ciLow": 0.5738567539698343,
          "ciHigh": 1.2802739925400284,
          "inDear": 30,
          "inBase": 35,
          "shareDear": 0.3,
          "shareBase": 0.35,
          "significant": false,
          "desecrated": false,
          "tierRange": "P1-P5",
          "tierDear": "P2",
          "tierMarket": "P2"
        },
        {
          "key": "exp|# to Accuracy Rating",
          "label": "# to Accuracy Rating",
          "lift": 0.8947368421052632,
          "ciLow": 0.4946227491310862,
          "ciHigh": 1.6185143486158855,
          "inDear": 17,
          "inBase": 19,
          "shareDear": 0.17,
          "shareBase": 0.19,
          "significant": false,
          "desecrated": false,
          "tierRange": "P1-P7",
          "tierDear": "P4",
          "tierMarket": "P3"
        }
      ],
      "suffixes": [
        {
          "key": "exp|#% to Fire Resistance",
          "label": "#% to Fire Resistance",
          "lift": 1.2692307692307692,
          "ciLow": 0.8233203412470633,
          "ciHigh": 1.956646356049054,
          "inDear": 33,
          "inBase": 26,
          "shareDear": 0.33,
          "shareBase": 0.26,
          "significant": false,
          "desecrated": false,
          "tierRange": "S1-S6",
          "tierDear": "S2",
          "tierMarket": "S2"
        },
        {
          "key": "exp|#% to Lightning Resistance",
          "label": "#% to Lightning Resistance",
          "lift": 1,
          "ciLow": 0.6187215230044476,
          "ciHigh": 1.6162360008814687,
          "inDear": 25,
          "inBase": 25,
          "shareDear": 0.25,
          "shareBase": 0.25,
          "significant": false,
          "desecrated": false,
          "tierRange": "S1-S6",
          "tierDear": "S2",
          "tierMarket": "S4"
        },
        {
          "key": "exp|#% of Armour also applies to Elemental Damage",
          "label": "#% of Armour also applies to Elemental Damage",
          "lift": 1.0526315789473684,
          "ciLow": 0.5992223167523283,
          "ciHigh": 1.8491187828293187,
          "inDear": 20,
          "inBase": 19,
          "shareDear": 0.2,
          "shareBase": 0.19,
          "significant": false,
          "desecrated": false,
          "tierRange": "S1-S3",
          "tierDear": "S2",
          "tierMarket": "S1"
        },
        {
          "key": "exp|#% increased Attack Speed",
          "label": "#% increased Attack Speed",
          "lift": 1.3,
          "ciLow": 0.5980621033558006,
          "ciHigh": 2.8257934928784167,
          "inDear": 13,
          "inBase": 10,
          "shareDear": 0.13,
          "shareBase": 0.1,
          "significant": false,
          "desecrated": false,
          "tierRange": "S1-S2",
          "tierDear": "S1",
          "tierMarket": "S1"
        },
        {
          "key": "exp|#% to Chaos Resistance",
          "label": "#% to Chaos Resistance",
          "lift": 1.3,
          "ciLow": 0.5980621033558006,
          "ciHigh": 2.8257934928784167,
          "inDear": 13,
          "inBase": 10,
          "shareDear": 0.13,
          "shareBase": 0.1,
          "significant": false,
          "desecrated": false,
          "tierRange": "S1-S5",
          "tierDear": "S2",
          "tierMarket": "S3"
        },
        {
          "key": "exp|Leech #% of Physical Attack Damage as Life",
          "label": "Leech #% of Physical Attack Damage as Life",
          "lift": 1.2222222222222223,
          "ciLow": 0.5296492481131941,
          "ciHigh": 2.8204083472512993,
          "inDear": 11,
          "inBase": 9,
          "shareDear": 0.11,
          "shareBase": 0.09,
          "significant": false,
          "desecrated": false,
          "tierRange": "S1-S4",
          "tierDear": "S1",
          "tierMarket": "S1"
        }
      ]
    },
    {
      "key": "armour.chest/ar/es",
      "label": "Body Armour — Armour + Energy Shield",
      "group": "Body Armour / ar/es",
      "section": "Armour",
      "at": "2026-07-17T12:35:16.687Z",
      "minIlvl": 70,
      "total": 1399,
      "ladder": [
        {
          "minEx": 1,
          "count": 1399
        },
        {
          "minEx": 50,
          "count": 688
        },
        {
          "minEx": 200,
          "count": 547
        },
        {
          "minEx": 1000,
          "count": 242
        },
        {
          "minEx": 5000,
          "count": 83
        }
      ],
      "dearThresholdEx": 1000,
      "dearCount": 242,
      "nDear": 100,
      "nBase": 100,
      "snapshots": 1,
      "trendPct": null,
      "bases": [
        {
          "key": "Conjurer Mantle",
          "label": "Conjurer Mantle",
          "lift": 1.0256410256410258,
          "ciLow": 0.7277687561700388,
          "ciHigh": 1.445430989664794,
          "inDear": 40,
          "inBase": 39,
          "shareDear": 0.4,
          "shareBase": 0.39,
          "significant": false
        },
        {
          "key": "Wolfskin Mantle",
          "label": "Wolfskin Mantle",
          "lift": 0.9411764705882353,
          "ciLow": 0.5043326439626228,
          "ciHigh": 1.7564065292877946,
          "inDear": 16,
          "inBase": 17,
          "shareDear": 0.16,
          "shareBase": 0.17,
          "significant": false
        },
        {
          "key": "Seastorm Mantle",
          "label": "Seastorm Mantle",
          "lift": 0.923076923076923,
          "ciLow": 0.4430472622674454,
          "ciHigh": 1.923205667847705,
          "inDear": 12,
          "inBase": 13,
          "shareDear": 0.12,
          "shareBase": 0.13,
          "significant": false
        }
      ],
      "prefixes": [
        {
          "key": "exp|#% increased Armour and Energy Shield",
          "label": "#% increased Armour and Energy Shield",
          "lift": 1.1842105263157894,
          "ciLow": 0.8504154041078501,
          "ciHigh": 1.6490230114167492,
          "inDear": 45,
          "inBase": 38,
          "shareDear": 0.45,
          "shareBase": 0.38,
          "significant": false,
          "desecrated": false,
          "tierRange": "P1-P7",
          "tierDear": "P3",
          "tierMarket": "P2"
        },
        {
          "key": "exp|# to maximum Life",
          "label": "# to maximum Life",
          "lift": 0.9787234042553192,
          "ciLow": 0.7269798440126879,
          "ciHigh": 1.317642448998081,
          "inDear": 46,
          "inBase": 47,
          "shareDear": 0.46,
          "shareBase": 0.47,
          "significant": false,
          "desecrated": false,
          "tierRange": "P1-P13",
          "tierDear": "P4",
          "tierMarket": "P3"
        },
        {
          "key": "exp|# to Armour / # to maximum Energy Shield",
          "label": "# to Armour / # to maximum Energy Shield",
          "lift": 1,
          "ciLow": 0.6964959400071032,
          "ciHigh": 1.4357585486999414,
          "inDear": 37,
          "inBase": 37,
          "shareDear": 0.37,
          "shareBase": 0.37,
          "significant": false,
          "desecrated": false,
          "tierRange": "P1-P8",
          "tierDear": "P3",
          "tierMarket": "P3"
        },
        {
          "key": "exp|# to maximum Life / #% increased Armour and Energy Shield",
          "label": "#% increased Armour and Energy Shield / # to maximum Life",
          "lift": 0.9642857142857143,
          "ciLow": 0.6147536232364346,
          "ciHigh": 1.5125521894124576,
          "inDear": 27,
          "inBase": 28,
          "shareDear": 0.27,
          "shareBase": 0.28,
          "significant": false,
          "desecrated": false,
          "tierRange": "P1-P6",
          "tierDear": "P2",
          "tierMarket": "P3"
        },
        {
          "key": "exp|# to Armour / # to maximum Energy Shield / #% increased Armour and Energy Shield",
          "label": "# to Armour / # to maximum Energy Shield / #% increased Armour and Energy Shield",
          "lift": 0.7857142857142857,
          "ciLow": 0.4838812323993153,
          "ciHigh": 1.275823275299205,
          "inDear": 22,
          "inBase": 28,
          "shareDear": 0.22,
          "shareBase": 0.28,
          "significant": false,
          "desecrated": false,
          "tierRange": "P1-P6",
          "tierDear": "P1",
          "tierMarket": "P2"
        },
        {
          "key": "exp|# to # Physical Thorns damage",
          "label": "# to # Physical Thorns damage",
          "lift": 0.4,
          "ciLow": 0.20285686474039127,
          "ciHigh": 0.7887334757182711,
          "inDear": 10,
          "inBase": 25,
          "shareDear": 0.1,
          "shareBase": 0.25,
          "significant": true,
          "desecrated": false,
          "tierRange": "P1-P6",
          "tierDear": "P2",
          "tierMarket": "P3"
        }
      ],
      "suffixes": [
        {
          "key": "exp|#% to Cold Resistance",
          "label": "#% to Cold Resistance",
          "lift": 1.8181818181818183,
          "ciLow": 1.1706744678793135,
          "ciHigh": 2.8238295227839045,
          "inDear": 40,
          "inBase": 22,
          "shareDear": 0.4,
          "shareBase": 0.22,
          "significant": true,
          "desecrated": false,
          "tierRange": "S1-S6",
          "tierDear": "S3",
          "tierMarket": "S3"
        },
        {
          "key": "exp|# to Spirit",
          "label": "# to Spirit",
          "lift": 1.6666666666666667,
          "ciLow": 1.0913519311095856,
          "ciHigh": 2.5452630802179375,
          "inDear": 40,
          "inBase": 24,
          "shareDear": 0.4,
          "shareBase": 0.24,
          "significant": true,
          "desecrated": false,
          "tierRange": "P1-P7",
          "tierDear": "P3",
          "tierMarket": "P4"
        },
        {
          "key": "exp|#% to Fire Resistance",
          "label": "#% to Fire Resistance",
          "lift": 1.303030303030303,
          "ciLow": 0.9099539544016365,
          "ciHigh": 1.8659053707082711,
          "inDear": 43,
          "inBase": 33,
          "shareDear": 0.43,
          "shareBase": 0.33,
          "significant": false,
          "desecrated": false,
          "tierRange": "S1-S8",
          "tierDear": "S3",
          "tierMarket": "S3"
        },
        {
          "key": "exp|#% to Lightning Resistance",
          "label": "#% to Lightning Resistance",
          "lift": 1.1875,
          "ciLow": 0.8121786864893337,
          "ciHigh": 1.7362635506915873,
          "inDear": 38,
          "inBase": 32,
          "shareDear": 0.38,
          "shareBase": 0.32,
          "significant": false,
          "desecrated": false,
          "tierRange": "S1-S7",
          "tierDear": "S4",
          "tierMarket": "S3"
        },
        {
          "key": "exp|#% to Chaos Resistance",
          "label": "#% to Chaos Resistance",
          "lift": 1.7500000000000002,
          "ciLow": 0.7682417044348651,
          "ciHigh": 3.986375618924308,
          "inDear": 14,
          "inBase": 8,
          "shareDear": 0.14,
          "shareBase": 0.08,
          "significant": false,
          "desecrated": false,
          "tierRange": "S1-S6",
          "tierDear": "S2",
          "tierMarket": "S2"
        },
        {
          "key": "exp|#% of Armour also applies to Elemental Damage",
          "label": "#% of Armour also applies to Elemental Damage",
          "lift": 1.0625,
          "ciLow": 0.5693442738484297,
          "ciHigh": 1.9828183084537994,
          "inDear": 17,
          "inBase": 16,
          "shareDear": 0.17,
          "shareBase": 0.16,
          "significant": false,
          "desecrated": false,
          "tierRange": "S1-S4",
          "tierDear": "S2",
          "tierMarket": "S3"
        }
      ]
    },
    {
      "key": "armour.boots/ar",
      "label": "Boots — Armour",
      "group": "Boots / ar",
      "section": "Armour",
      "at": "2026-07-17T14:00:52.250Z",
      "minIlvl": 70,
      "total": 1376,
      "ladder": [
        {
          "minEx": 1,
          "count": 1376
        },
        {
          "minEx": 50,
          "count": 772
        },
        {
          "minEx": 200,
          "count": 600
        },
        {
          "minEx": 1000,
          "count": 283
        },
        {
          "minEx": 5000,
          "count": 113
        }
      ],
      "dearThresholdEx": 1000,
      "dearCount": 283,
      "nDear": 100,
      "nBase": 100,
      "snapshots": 1,
      "trendPct": null,
      "bases": [
        {
          "key": "Tasalian Greaves",
          "label": "Tasalian Greaves",
          "lift": 0.9729729729729729,
          "ciLow": 0.6749899524186206,
          "ciHigh": 1.402504441353148,
          "inDear": 36,
          "inBase": 37,
          "shareDear": 0.36,
          "shareBase": 0.37,
          "significant": false
        },
        {
          "key": "Vaal Greaves",
          "label": "Vaal Greaves",
          "lift": 0.95,
          "ciLow": 0.5407981408689763,
          "ciHigh": 1.66882970150346,
          "inDear": 19,
          "inBase": 20,
          "shareDear": 0.19,
          "shareBase": 0.2,
          "significant": false
        },
        {
          "key": "Ornate Greaves",
          "label": "Ornate Greaves",
          "lift": 0.631578947368421,
          "ciLow": 0.3240092200605719,
          "ciHigh": 1.2311130117977254,
          "inDear": 12,
          "inBase": 19,
          "shareDear": 0.12,
          "shareBase": 0.19,
          "significant": false
        }
      ],
      "prefixes": [
        {
          "key": "exp|#% increased Movement Speed",
          "label": "#% increased Movement Speed",
          "lift": 1.1964285714285714,
          "ciLow": 0.9586240933543044,
          "ciHigh": 1.4932248588932098,
          "inDear": 67,
          "inBase": 56,
          "shareDear": 0.67,
          "shareBase": 0.56,
          "significant": false,
          "desecrated": false,
          "tierRange": "P1-P4",
          "tierDear": "P2",
          "tierMarket": "P2"
        },
        {
          "key": "exp|# to maximum Life",
          "label": "# to maximum Life",
          "lift": 1.2285714285714286,
          "ciLow": 0.8660473501456978,
          "ciHigh": 1.7428466871333446,
          "inDear": 43,
          "inBase": 35,
          "shareDear": 0.43,
          "shareBase": 0.35,
          "significant": false,
          "desecrated": false,
          "tierRange": "P1-P9",
          "tierDear": "P2",
          "tierMarket": "P2"
        },
        {
          "key": "exp|# to maximum Mana",
          "label": "# to maximum Mana",
          "lift": 1.1153846153846152,
          "ciLow": 0.7104978108223476,
          "ciHigh": 1.7510016516402125,
          "inDear": 29,
          "inBase": 26,
          "shareDear": 0.29,
          "shareBase": 0.26,
          "significant": false,
          "desecrated": false,
          "tierRange": "P1-P9",
          "tierDear": "P3",
          "tierMarket": "P2"
        },
        {
          "key": "exp|#% increased Armour",
          "label": "#% increased Armour",
          "lift": 0.9743589743589743,
          "ciLow": 0.6863591247494214,
          "ciHigh": 1.3832050550219959,
          "inDear": 38,
          "inBase": 39,
          "shareDear": 0.38,
          "shareBase": 0.39,
          "significant": false,
          "desecrated": false,
          "tierRange": "P1-P7",
          "tierDear": "P2",
          "tierMarket": "P3"
        },
        {
          "key": "exp|# to Stun Threshold / #% increased Armour",
          "label": "#% increased Armour / # to Stun Threshold",
          "lift": 0.9642857142857143,
          "ciLow": 0.6147536232364346,
          "ciHigh": 1.5125521894124576,
          "inDear": 27,
          "inBase": 28,
          "shareDear": 0.27,
          "shareBase": 0.28,
          "significant": false,
          "desecrated": false,
          "tierRange": "P1-P5",
          "tierDear": "P2",
          "tierMarket": "P2"
        },
        {
          "key": "exp|# to Armour",
          "label": "# to Armour",
          "lift": 0.7142857142857143,
          "ciLow": 0.4637381592521494,
          "ciHigh": 1.1001986173737293,
          "inDear": 25,
          "inBase": 35,
          "shareDear": 0.25,
          "shareBase": 0.35,
          "significant": false,
          "desecrated": false,
          "tierRange": "P1-P7",
          "tierDear": "P2",
          "tierMarket": "P2"
        }
      ],
      "suffixes": [
        {
          "key": "exp|#% to Lightning Resistance",
          "label": "#% to Lightning Resistance",
          "lift": 1.7499999999999998,
          "ciLow": 1.2057478736500258,
          "ciHigh": 2.539917396436483,
          "inDear": 49,
          "inBase": 28,
          "shareDear": 0.49,
          "shareBase": 0.28,
          "significant": true,
          "desecrated": false,
          "tierRange": "S1-S5",
          "tierDear": "S3",
          "tierMarket": "S3"
        },
        {
          "key": "exp|#% to Cold Resistance",
          "label": "#% to Cold Resistance",
          "lift": 1.0810810810810811,
          "ciLow": 0.7612435368972568,
          "ciHigh": 1.5352988199217787,
          "inDear": 40,
          "inBase": 37,
          "shareDear": 0.4,
          "shareBase": 0.37,
          "significant": false,
          "desecrated": false,
          "tierRange": "S1-S8",
          "tierDear": "S2",
          "tierMarket": "S2"
        },
        {
          "key": "exp|#% to Fire Resistance",
          "label": "#% to Fire Resistance",
          "lift": 1.0256410256410258,
          "ciLow": 0.7277687561700388,
          "ciHigh": 1.445430989664794,
          "inDear": 40,
          "inBase": 39,
          "shareDear": 0.4,
          "shareBase": 0.39,
          "significant": false,
          "desecrated": false,
          "tierRange": "S1-S8",
          "tierDear": "S3",
          "tierMarket": "S2"
        },
        {
          "key": "exp|#% to Chaos Resistance",
          "label": "#% to Chaos Resistance",
          "lift": 1,
          "ciLow": 0.48818257397584236,
          "ciHigh": 2.048413960899565,
          "inDear": 13,
          "inBase": 13,
          "shareDear": 0.13,
          "shareBase": 0.13,
          "significant": false,
          "desecrated": false,
          "tierRange": "S1-S3",
          "tierDear": "S2",
          "tierMarket": "S2"
        },
        {
          "key": "exp|#% of Armour also applies to Elemental Damage",
          "label": "#% of Armour also applies to Elemental Damage",
          "lift": 0.7857142857142857,
          "ciLow": 0.4838812323993153,
          "ciHigh": 1.275823275299205,
          "inDear": 22,
          "inBase": 28,
          "shareDear": 0.22,
          "shareBase": 0.28,
          "significant": false,
          "desecrated": false,
          "tierRange": "S1-S5",
          "tierDear": "S2",
          "tierMarket": "S2"
        },
        {
          "key": "exp|# to Stun Threshold",
          "label": "# to Stun Threshold",
          "lift": 0.8333333333333334,
          "ciLow": 0.4453134441725656,
          "ciHigh": 1.5594508846118216,
          "inDear": 15,
          "inBase": 18,
          "shareDear": 0.15,
          "shareBase": 0.18,
          "significant": false,
          "desecrated": false,
          "tierRange": "S1-S8",
          "tierDear": "S2",
          "tierMarket": "S2"
        }
      ]
    },
    {
      "key": "armour.helmet/ar",
      "label": "Helmet — Armour",
      "group": "Helmet / ar",
      "section": "Armour",
      "at": "2026-07-18T02:27:50.739Z",
      "minIlvl": 70,
      "total": 1329,
      "ladder": [
        {
          "minEx": 1,
          "count": 1329
        },
        {
          "minEx": 50,
          "count": 739
        },
        {
          "minEx": 200,
          "count": 561
        },
        {
          "minEx": 1000,
          "count": 240
        },
        {
          "minEx": 5000,
          "count": 90
        }
      ],
      "dearThresholdEx": 1000,
      "dearCount": 240,
      "nDear": 100,
      "nBase": 100,
      "snapshots": 1,
      "trendPct": null,
      "bases": [
        {
          "key": "Imperial Greathelm",
          "label": "Imperial Greathelm",
          "lift": 1.4166666666666667,
          "ciLow": 0.909678672722768,
          "ciHigh": 2.206212484280235,
          "inDear": 34,
          "inBase": 24,
          "shareDear": 0.34,
          "shareBase": 0.24,
          "significant": false
        },
        {
          "key": "Masked Greathelm",
          "label": "Masked Greathelm",
          "lift": 0.8571428571428571,
          "ciLow": 0.48703717381824213,
          "ciHigh": 1.5084965112441322,
          "inDear": 18,
          "inBase": 21,
          "shareDear": 0.18,
          "shareBase": 0.21,
          "significant": false
        },
        {
          "key": "Paragon Greathelm",
          "label": "Paragon Greathelm",
          "lift": 1.1052631578947367,
          "ciLow": 0.6343490299589374,
          "ciHigh": 1.9257641936940022,
          "inDear": 21,
          "inBase": 19,
          "shareDear": 0.21,
          "shareBase": 0.19,
          "significant": false
        }
      ],
      "prefixes": [
        {
          "key": "exp|#% increased Armour / # to maximum Mana",
          "label": "#% increased Armour / # to maximum Mana",
          "lift": 1.5294117647058822,
          "ciLow": 0.8869199307582948,
          "ciHigh": 2.6373297801763096,
          "inDear": 26,
          "inBase": 17,
          "shareDear": 0.26,
          "shareBase": 0.17,
          "significant": false,
          "desecrated": false,
          "tierRange": "P1-P4",
          "tierDear": "P2",
          "tierMarket": "P2"
        },
        {
          "key": "exp|# to maximum Life",
          "label": "# to maximum Life",
          "lift": 1,
          "ciLow": 0.731463599063997,
          "ciHigh": 1.3671220294210542,
          "inDear": 44,
          "inBase": 44,
          "shareDear": 0.44,
          "shareBase": 0.44,
          "significant": false,
          "desecrated": false,
          "tierRange": "P1-P10",
          "tierDear": "P2",
          "tierMarket": "P2"
        },
        {
          "key": "exp|# to Armour",
          "label": "# to Armour",
          "lift": 1.0666666666666667,
          "ciLow": 0.7051738661894102,
          "ciHigh": 1.6134712761351393,
          "inDear": 32,
          "inBase": 30,
          "shareDear": 0.32,
          "shareBase": 0.3,
          "significant": false,
          "desecrated": false,
          "tierRange": "P1-P6",
          "tierDear": "P2",
          "tierMarket": "P1"
        },
        {
          "key": "exp|# to maximum Mana",
          "label": "# to maximum Mana",
          "lift": 0.9642857142857143,
          "ciLow": 0.6147536232364346,
          "ciHigh": 1.5125521894124576,
          "inDear": 27,
          "inBase": 28,
          "shareDear": 0.27,
          "shareBase": 0.28,
          "significant": false,
          "desecrated": false,
          "tierRange": "P1-P6",
          "tierDear": "P2",
          "tierMarket": "P2"
        },
        {
          "key": "exp|#% increased Armour",
          "label": "#% increased Armour",
          "lift": 0.8604651162790697,
          "ciLow": 0.611793341652783,
          "ciHigh": 1.210212936173731,
          "inDear": 37,
          "inBase": 43,
          "shareDear": 0.37,
          "shareBase": 0.43,
          "significant": false,
          "desecrated": false,
          "tierRange": "P1-P5",
          "tierDear": "P2",
          "tierMarket": "P3"
        },
        {
          "key": "exp|#% increased Armour / # to maximum Life",
          "label": "#% increased Armour / # to maximum Life",
          "lift": 0.7999999999999999,
          "ciLow": 0.5508369481464552,
          "ciHigh": 1.1618683208408127,
          "inDear": 32,
          "inBase": 40,
          "shareDear": 0.32,
          "shareBase": 0.4,
          "significant": false,
          "desecrated": false,
          "tierRange": "P1-P5",
          "tierDear": "P1",
          "tierMarket": "P2"
        }
      ],
      "suffixes": [
        {
          "key": "exp|#% to Fire Resistance",
          "label": "#% to Fire Resistance",
          "lift": 1.206896551724138,
          "ciLow": 0.803612552393468,
          "ciHigh": 1.8125641295986488,
          "inDear": 35,
          "inBase": 29,
          "shareDear": 0.35,
          "shareBase": 0.29,
          "significant": false,
          "desecrated": false,
          "tierRange": "S1-S6",
          "tierDear": "S3",
          "tierMarket": "S3"
        },
        {
          "key": "exp|#% to Lightning Resistance",
          "label": "#% to Lightning Resistance",
          "lift": 1.1379310344827587,
          "ciLow": 0.7515810154030231,
          "ciHigh": 1.7228841770898633,
          "inDear": 33,
          "inBase": 29,
          "shareDear": 0.33,
          "shareBase": 0.29,
          "significant": false,
          "desecrated": false,
          "tierRange": "S1-S8",
          "tierDear": "S2",
          "tierMarket": "S4"
        },
        {
          "key": "exp|#% to Cold Resistance",
          "label": "#% to Cold Resistance",
          "lift": 1.1379310344827587,
          "ciLow": 0.7515810154030231,
          "ciHigh": 1.7228841770898633,
          "inDear": 33,
          "inBase": 29,
          "shareDear": 0.33,
          "shareBase": 0.29,
          "significant": false,
          "desecrated": false,
          "tierRange": "S1-S5",
          "tierDear": "S2",
          "tierMarket": "S2"
        },
        {
          "key": "exp|#% of Armour also applies to Elemental Damage",
          "label": "#% of Armour also applies to Elemental Damage",
          "lift": 1.3333333333333335,
          "ciLow": 0.7249107810287672,
          "ciHigh": 2.452409074748233,
          "inDear": 20,
          "inBase": 15,
          "shareDear": 0.2,
          "shareBase": 0.15,
          "significant": false,
          "desecrated": false,
          "tierRange": "S1-S5",
          "tierDear": "S1",
          "tierMarket": "S1"
        },
        {
          "key": "exp|#% increased Rarity of Items found",
          "label": "#% increased Rarity of Items found",
          "lift": 1.1363636363636365,
          "ciLow": 0.688242031212959,
          "ciHigh": 1.876261918752271,
          "inDear": 25,
          "inBase": 22,
          "shareDear": 0.25,
          "shareBase": 0.22,
          "significant": false,
          "desecrated": false,
          "tierRange": "P1-S3",
          "tierDear": "P1",
          "tierMarket": "S1"
        },
        {
          "key": "exp|#% increased Critical Hit Chance",
          "label": "#% increased Critical Hit Chance",
          "lift": 1.4444444444444446,
          "ciLow": 0.6468001639341238,
          "ciHigh": 3.2257563764299246,
          "inDear": 13,
          "inBase": 9,
          "shareDear": 0.13,
          "shareBase": 0.09,
          "significant": false,
          "desecrated": false,
          "tierRange": "S1-S3",
          "tierDear": "S1",
          "tierMarket": "S1"
        }
      ]
    },
    {
      "key": "armour.chest/ar",
      "label": "Body Armour — Armour",
      "group": "Body Armour / ar",
      "section": "Armour",
      "at": "2026-07-17T11:56:10.539Z",
      "minIlvl": 70,
      "total": 1305,
      "ladder": [
        {
          "minEx": 1,
          "count": 1305
        },
        {
          "minEx": 50,
          "count": 675
        },
        {
          "minEx": 200,
          "count": 529
        },
        {
          "minEx": 1000,
          "count": 183
        },
        {
          "minEx": 5000,
          "count": 65
        }
      ],
      "dearThresholdEx": 1000,
      "dearCount": 183,
      "nDear": 100,
      "nBase": 100,
      "snapshots": 1,
      "trendPct": null,
      "bases": [
        {
          "key": "Soldier Cuirass",
          "label": "Soldier Cuirass",
          "lift": 1.2307692307692308,
          "ciLow": 0.7950391727212189,
          "ciHigh": 1.905305991682812,
          "inDear": 32,
          "inBase": 26,
          "shareDear": 0.32,
          "shareBase": 0.26,
          "significant": false
        },
        {
          "key": "Warlord Cuirass",
          "label": "Warlord Cuirass",
          "lift": 1.1304347826086956,
          "ciLow": 0.6940600822775931,
          "ciHigh": 1.8411702824604637,
          "inDear": 26,
          "inBase": 23,
          "shareDear": 0.26,
          "shareBase": 0.23,
          "significant": false
        },
        {
          "key": "Ornate Plate",
          "label": "Ornate Plate",
          "lift": 0.7142857142857143,
          "ciLow": 0.39128877996942196,
          "ciHigh": 1.303906750591019,
          "inDear": 15,
          "inBase": 21,
          "shareDear": 0.15,
          "shareBase": 0.21,
          "significant": false
        }
      ],
      "prefixes": [
        {
          "key": "exp|#% increased Armour",
          "label": "#% increased Armour",
          "lift": 1.1749999999999998,
          "ciLow": 0.8551751516030294,
          "ciHigh": 1.6144353556251165,
          "inDear": 47,
          "inBase": 40,
          "shareDear": 0.47,
          "shareBase": 0.4,
          "significant": false,
          "desecrated": false,
          "tierRange": "P1-P8",
          "tierDear": "P2",
          "tierMarket": "P2"
        },
        {
          "key": "exp|# to maximum Life",
          "label": "# to maximum Life",
          "lift": 1.0851063829787235,
          "ciLow": 0.817446046472619,
          "ciHigh": 1.4404080458423356,
          "inDear": 51,
          "inBase": 47,
          "shareDear": 0.51,
          "shareBase": 0.47,
          "significant": false,
          "desecrated": false,
          "tierRange": "P1-P12",
          "tierDear": "P3",
          "tierMarket": "P4"
        },
        {
          "key": "exp|# to Armour",
          "label": "# to Armour",
          "lift": 1.0625,
          "ciLow": 0.8028384588958363,
          "ciHigh": 1.40614371109303,
          "inDear": 51,
          "inBase": 48,
          "shareDear": 0.51,
          "shareBase": 0.48,
          "significant": false,
          "desecrated": false,
          "tierRange": "P1-P11",
          "tierDear": "P2",
          "tierMarket": "P3"
        },
        {
          "key": "exp|# to maximum Life / #% increased Armour",
          "label": "#% increased Armour / # to maximum Life",
          "lift": 1.2,
          "ciLow": 0.7631344474440681,
          "ciHigh": 1.8869545265882404,
          "inDear": 30,
          "inBase": 25,
          "shareDear": 0.3,
          "shareBase": 0.25,
          "significant": false,
          "desecrated": false,
          "tierRange": "P1-P6",
          "tierDear": "P2",
          "tierMarket": "P2"
        },
        {
          "key": "exp|# to Armour / #% increased Armour",
          "label": "# to Armour / #% increased Armour",
          "lift": 0.8620689655172414,
          "ciLow": 0.5455754173247971,
          "ciHigh": 1.3621634657808273,
          "inDear": 25,
          "inBase": 29,
          "shareDear": 0.25,
          "shareBase": 0.29,
          "significant": false,
          "desecrated": false,
          "tierRange": "P1-P4",
          "tierDear": "P2",
          "tierMarket": "P2"
        },
        {
          "key": "exp|# to # Physical Thorns damage",
          "label": "# to # Physical Thorns damage",
          "lift": 0.5882352941176471,
          "ciLow": 0.28339736965245893,
          "ciHigh": 1.2209737926291033,
          "inDear": 10,
          "inBase": 17,
          "shareDear": 0.1,
          "shareBase": 0.17,
          "significant": false,
          "desecrated": false,
          "tierRange": "P1-P4",
          "tierDear": "P2",
          "tierMarket": "P2"
        }
      ],
      "suffixes": [
        {
          "key": "exp|#% to Lightning Resistance",
          "label": "#% to Lightning Resistance",
          "lift": 1.310344827586207,
          "ciLow": 0.8819647237377828,
          "ciHigh": 1.946793926071367,
          "inDear": 38,
          "inBase": 29,
          "shareDear": 0.38,
          "shareBase": 0.29,
          "significant": false,
          "desecrated": false,
          "tierRange": "S1-S8",
          "tierDear": "S3",
          "tierMarket": "S3"
        },
        {
          "key": "exp|#% to Cold Resistance",
          "label": "#% to Cold Resistance",
          "lift": 1.3214285714285714,
          "ciLow": 0.8811772750109178,
          "ciHigh": 1.9816369746554345,
          "inDear": 37,
          "inBase": 28,
          "shareDear": 0.37,
          "shareBase": 0.28,
          "significant": false,
          "desecrated": false,
          "tierRange": "S1-S7",
          "tierDear": "S2",
          "tierMarket": "S3"
        },
        {
          "key": "exp|#% of Armour also applies to Elemental Damage",
          "label": "#% of Armour also applies to Elemental Damage",
          "lift": 1.2272727272727273,
          "ciLow": 0.7518844756721224,
          "ciHigh": 2.0032310758391727,
          "inDear": 27,
          "inBase": 22,
          "shareDear": 0.27,
          "shareBase": 0.22,
          "significant": false,
          "desecrated": false,
          "tierRange": "S1-S6",
          "tierDear": "S2",
          "tierMarket": "S2"
        },
        {
          "key": "exp|#% to Fire Resistance",
          "label": "#% to Fire Resistance",
          "lift": 1.1818181818181819,
          "ciLow": 0.7200275005268533,
          "ciHigh": 1.9397789860165822,
          "inDear": 26,
          "inBase": 22,
          "shareDear": 0.26,
          "shareBase": 0.22,
          "significant": false,
          "desecrated": false,
          "tierRange": "S1-S8",
          "tierDear": "S2",
          "tierMarket": "S3"
        },
        {
          "key": "exp|#% reduced Attribute Requirements",
          "label": "#% reduced Attribute Requirements",
          "lift": 1.4000000000000001,
          "ciLow": 0.6529604502296472,
          "ciHigh": 3.0017131961218553,
          "inDear": 14,
          "inBase": 10,
          "shareDear": 0.14,
          "shareBase": 0.1,
          "significant": false,
          "desecrated": false,
          "tierRange": "S1-S4",
          "tierDear": "S2",
          "tierMarket": "S2"
        },
        {
          "key": "exp|# to Spirit",
          "label": "# to Spirit",
          "lift": 1,
          "ciLow": 0.5933779595997004,
          "ciHigh": 1.6852665048000965,
          "inDear": 22,
          "inBase": 22,
          "shareDear": 0.22,
          "shareBase": 0.22,
          "significant": false,
          "desecrated": false,
          "tierRange": "P1-P8",
          "tierDear": "P3",
          "tierMarket": "P4"
        }
      ]
    }
  ]
}